Metadata-Version: 2.4
Name: gobox
Version: 0.0.1
Summary: Support for the That Little Box USB Go Box
Author-email: Daniel Jones <dan-code@erase.net>
License: MIT
Requires-Python: >=3.9
Requires-Dist: gobox
Requires-Dist: mido
Requires-Dist: python-rtmidi
